Workbook
Name lista_planos: 'Apoio'!$A$4:$A$7
Name lista_tipos: 'Apoio'!$B$4:$B$7
Name lista_renovacao: 'Apoio'!$C$4:$C$6
Name filtro_plano: 'Dashboard'!$C$6
Name filtro_tipo: 'Dashboard'!$G$6
Name filtro_renovacao: 'Dashboard'!$K$6
Name base_id: 'Base'!$A$5:$A$299
Name base_plano: 'Base'!$C$5:$C$299
Name base_inicio: 'Base'!$D$5:$D$299
Name base_renovacao: 'Base'!$E$5:$E$299
Name base_preco: 'Base'!$F$5:$F$299
Name base_tipo: 'Base'!$G$5:$G$299
Name base_ea: 'Base'!$I$5:$I$299
Name base_minecraft: 'Base'!$K$5:$K$299
Name base_cupom: 'Base'!$L$5:$L$299
Name base_total: 'Base'!$M$5:$M$299

Sheet Dashboard
A1: XBOX SALES PULSE | J1: PROJETO AUTORAL • DIO
J2: DASHBOARD | K2: ANÁLISE | L2: BASE | M2: DICIONÁRIO | N2: GUIA
A3: Dashboard autoral de assinaturas: receita, planos, recorrência e adicionais em uma visão executiva.
A4: ="Base didática: "&Análise!B7&" assinaturas • período "&TEXT(MIN(Base!D5:D299),"dd/mm/yyyy")&" a "&TEXT(MAX(Base!D5:D299),"dd/mm/yyyy")&" • valores em US$" -> Base didática: 295 assinaturas • período 01/01/2024 a 16/12/2024 • valores em US$
A5: FILTROS INTERATIVOS — selecione uma opção nas células verdes
A6: PLANO | C6: Todos | E6: PERIODICIDADE | G6: Todos | I6: RENOVAÇÃO | K6: Todos | M6: Para limpar: escolha Todos
A8: ="Filtros ativos: Plano = "&filtro_plano&" • Periodicidade = "&filtro_tipo&" • Renovação = "&filtro_renovacao -> Filtros ativos: Plano = Todos • Periodicidade = Todos • Renovação = Todos
A10: RECEITA TOTAL | D10: ASSINANTES | G10: TICKET MÉDIO | J10: % AUTO RENOVAÇÃO | M10: BASE VALIDADA
A11: =Análise!B6 -> 7633 | D11: =Análise!B7 -> 295 | G11: =Análise!B8 -> 25.874576 | J11: =Análise!B9 -> 0.50169492 | M11: =Análise!B14 -> 1
A15: RECEITA DOS PLANOS | D15: EA PLAY | G15: MINECRAFT | J15: CUPONS CONCEDIDOS | M15: REGISTROS
A16: =Análise!B10 -> 2935 | D16: =Análise!B11 -> 2940 | G16: =Análise!B12 -> 3880 | J16: =Análise!B13 -> 2122 | M16: =Análise!B7 -> 295
A20: VISUALIZAÇÕES DINÂMICAS
A51: PERGUNTAS-CHAVE DO DESAFIO — BASE COMPLETA
A52: Planos anuais $ 1.754,00 | D52: Anual com renovação $ 1.537,00 | G52: Anual sem renovação $ 217,00 | J52: EA Play $ 2.940,00 | M52: Minecraft $ 3.880,00
A56: Projeto autoral: 0Barone (@gabrielnasciimentoleandro-arch) • Base didática DIO • dashboard não oficial • Xbox, Game Pass, EA Play e Minecraft pertencem aos respectivos titulares.

Sheet Análise
A1: ANÁLISE E CÁLCULOS | J1: PROJETO AUTORAL • DIO
J2: DASHBOARD | K2: ANÁLISE | L2: BASE | M2: DICIONÁRIO | N2: GUIA
A3: Camada transparente de fórmulas que alimenta os cartões e gráficos do Dashboard.
A4: ="Filtros: "&filtro_plano&" | "&filtro_tipo&" | "&filtro_renovacao -> Filtros: Todos | Todos | Todos
A5: Indicador dinâmico | B5: Resultado | C5: Fórmula / interpretação
A6: Receita total | B6: =SUMIFS(Base!$M$5:$M$299,Base!$C$5:$C$299,IF(filtro_plano="Todos","*",filtro_plano),Base!$G$5:$G$299,IF(filtro_tipo="Todos","*",filtro_tipo),Base!$E$5:$E$299,IF(filtro_renovacao="Todos","*",filtro_renovacao)) -> 7633 | C6: Soma de Total Value com os filtros ativos
A7: Assinantes | B7: =COUNTIFS(Base!$C$5:$C$299,IF(filtro_plano="Todos","*",filtro_plano),Base!$G$5:$G$299,IF(filtro_tipo="Todos","*",filtro_tipo),Base!$E$5:$E$299,IF(filtro_renovacao="Todos","*",filtro_renovacao)) -> 295 | C7: Quantidade de registros filtrados
A8: Ticket médio | B8: =IFERROR(B6/B7,0) -> 25.874576 | C8: Receita / assinantes
A9: % auto renovação | B9: =IFERROR(COUNTIFS(Base!$C$5:$C$299,IF(filtro_plano="Todos","*",filtro_plano),Base!$G$5:$G$299,IF(filtro_tipo="Todos","*",filtro_tipo),Base!$E$5:$E$299,IF(filtro_renovacao="Todos","*",filtro_renovacao),Base!$E$5:$E$299,"Yes")/B7,0) -> 0.50169492 | C9: Participação de Auto Renewal = Yes
A10: Receita dos planos | B10: =SUMIFS(Base!$F$5:$F$299,Base!$C$5:$C$299,IF(filtro_plano="Todos","*",filtro_plano),Base!$G$5:$G$299,IF(filtro_tipo="Todos","*",filtro_tipo),Base!$E$5:$E$299,IF(filtro_renovacao="Todos","*",filtro_renovacao)) -> 2935 | C10: Subscription Price
A11: EA Play | B11: =SUMIFS(Base!$I$5:$I$299,Base!$C$5:$C$299,IF(filtro_plano="Todos","*",filtro_plano),Base!$G$5:$G$299,IF(filtro_tipo="Todos","*",filtro_tipo),Base!$E$5:$E$299,IF(filtro_renovacao="Todos","*",filtro_renovacao)) -> 2940 | C11: Receita do passe adicional
A12: Minecraft | B12: =SUMIFS(Base!$K$5:$K$299,Base!$C$5:$C$299,IF(filtro_plano="Todos","*",filtro_plano),Base!$G$5:$G$299,IF(filtro_tipo="Todos","*",filtro_tipo),Base!$E$5:$E$299,IF(filtro_renovacao="Todos","*",filtro_renovacao)) -> 3880 | C12: Receita do passe adicional
A13: Cupons | B13: =SUMIFS(Base!$L$5:$L$299,Base!$C$5:$C$299,IF(filtro_plano="Todos","*",filtro_plano),Base!$G$5:$G$299,IF(filtro_tipo="Todos","*",filtro_tipo),Base!$E$5:$E$299,IF(filtro_renovacao="Todos","*",filtro_renovacao)) -> 2122 | C13: Descontos concedidos
A14: Base validada | B14: =COUNTIF(Base!$O$5:$O$299,"OK")/COUNTA(Base!$A$5:$A$299) -> 1 | C14: Total Value = plano + adicionais − cupom
A16: PERGUNTAS DE NEGÓCIO — BASE COMPLETA, SEM FILTROS
A17: Receita de planos anuais | B17: =SUMIFS(Base!$M$5:$M$299,Base!$G$5:$G$299,"Annual") -> 1754
A18: Anual com auto renovação | B18: =SUMIFS(Base!$M$5:$M$299,Base!$G$5:$G$299,"Annual",Base!$E$5:$E$299,"Yes") -> 1537
A19: Anual sem auto renovação | B19: =SUMIFS(Base!$M$5:$M$299,Base!$G$5:$G$299,"Annual",Base!$E$5:$E$299,"No") -> 217
A20: EA Play Season Pass | B20: =SUM(Base!$I$5:$I$299) -> 2940
A21: Minecraft Season Pass | B21: =SUM(Base!$K$5:$K$299) -> 3880
A25: Mês | B25: Receita | C25: Assinantes | E25: Plano | F25: Receita | G25: Assinantes | I25: Auto Renewal | J25: Receita | K25: Assinantes
A26: 45292 | B26: =SUMIFS(Base!$M$5:$M$299,Base!$C$5:$C$299,IF(filtro_plano="Todos","*",filtro_plano),Base!$G$5:$G$299,IF(filtro_tipo="Todos","*",filtro_tipo),Base!$E$5:$E$299,IF(filtro_renovacao="Todos","*",filtro_renovacao),Base!$D$5:$D$299,">="&A26,Base!$D$5:$D$299,"<"&DATE(YEAR(A26),MONTH(A26)+1,1)) -> 65 | C26: =COUNTIFS(Base!$C$5:$C$299,IF(filtro_plano="Todos","*",filtro_plano),Base!$G$5:$G$299,IF(filtro_tipo="Todos","*",filtro_tipo),Base!$E$5:$E$299,IF(filtro_renovacao="Todos","*",filtro_renovacao),Base!$D$5:$D$299,">="&A26,Base!$D$5:$D$299,"<"&DATE(YEAR(A26),MONTH(A26)+1,1)) -> 2 | E26: Core | F26: =SUMIFS(Base!$M$5:$M$299,Base!$C$5:$C$299,IF(filtro_plano="Todos","*",filtro_plano),Base!$G$5:$G$299,IF(filtro_tipo="Todos","*",filtro_tipo),Base!$E$5:$E$299,IF(filtro_renovacao="Todos","*",filtro_renovacao),Base!$C$5:$C$299,E26) -> 444 | G26: =COUNTIFS(Base!$C$5:$C$299,IF(filtro_plano="Todos","*",filtro_plano),Base!$G$5:$G$299,IF(filtro_tipo="Todos","*",filtro_tipo),Base!$E$5:$E$299,IF(filtro_renovacao="Todos","*",filtro_renovacao),Base!$C$5:$C$299,E26) -> 101 | I26: Yes | J26: =SUMIFS(Base!$M$5:$M$299,Base!$C$5:$C$299,IF(filtro_plano="Todos","*",filtro_plano),Base!$G$5:$G$299,IF(filtro_tipo="Todos","*",filtro_tipo),Base!$E$5:$E$299,IF(filtro_renovacao="Todos","*",filtro_renovacao),Base!$E$5:$E$299,I26) -> 3786 | K26: =COUNTIFS(Base!$C$5:$C$299,IF(filtro_plano="Todos","*",filtro_plano),Base!$G$5:$G$299,IF(filtro_tipo="Todos","*",filtro_tipo),Base!$E$5:$E$299,IF(filtro_renovacao="Todos","*",filtro_renovacao),Base!$E$5:$E$299,I26) -> 148
A27: 45323 | B27: =SUMIFS(Base!$M$5:$M$299,Base!$C$5:$C$299,IF(filtro_plano="Todos","*",filtro_plano),Base!$G$5:$G$299,IF(filtro_tipo="Todos","*",filtro_tipo),Base!$E$5:$E$299,IF(filtro_renovacao="Todos","*",filtro_renovacao),Base!$D$5:$D$299,">="&A27,Base!$D$5:$D$299,"<"&DATE(YEAR(A27),MONTH(A27)+1,1)) -> 82 | C27: =COUNTIFS(Base!$C$5:$C$299,IF(filtro_plano="Todos","*",filtro_plano),Base!$G$5:$G$299,IF(filtro_tipo="Todos","*",filtro_tipo),Base!$E$5:$E$299,IF(filtro_renovacao="Todos","*",filtro_renovacao),Base!$D$5:$D$299,">="&A27,Base!$D$5:$D$299,"<"&DATE(YEAR(A27),MONTH(A27)+1,1)) -> 2 | E27: Standard | F27: =SUMIFS(Base!$M$5:$M$299,Base!$C$5:$C$299,IF(filtro_plano="Todos","*",filtro_plano),Base!$G$5:$G$299,IF(filtro_tipo="Todos","*",filtro_tipo),Base!$E$5:$E$299,IF(filtro_renovacao="Todos","*",filtro_renovacao),Base!$C$5:$C$299,E27) -> 1801 | G27: =COUNTIFS(Base!$C$5:$C$299,IF(filtro_plano="Todos","*",filtro_plano),Base!$G$5:$G$299,IF(filtro_tipo="Todos","*",filtro_tipo),Base!$E$5:$E$299,IF(filtro_renovacao="Todos","*",filtro_renovacao),Base!$C$5:$C$299,E27) -> 96 | I27: No | J27: =SUMIFS(Base!$M$5:$M$299,Base!$C$5:$C$299,IF(filtro_plano="Todos","*",filtro_plano),Base!$G$5:$G$299,IF(filtro_tipo="Todos","*",filtro_tipo),Base!$E$5:$E$299,IF(filtro_renovacao="Todos","*",filtro_renovacao),Base!$E$5:$E$299,I27) -> 3847 | K27: =COUNTIFS(Base!$C$5:$C$299,IF(filtro_plano="Todos","*",filtro_plano),Base!$G$5:$G$299,IF(filtro_tipo="Todos","*",filtro_tipo),Base!$E$5:$E$299,IF(filtro_renovacao="Todos","*",filtro_renovacao),Base!$E$5:$E$299,I27) -> 147
A28: 45352 | B28: =SUMIFS(Base!$M$5:$M$299,Base!$C$5:$C$299,IF(filtro_plano="Todos","*",filtro_plano),Base!$G$5:$G$299,IF(filtro_tipo="Todos","*",filtro_tipo),Base!$E$5:$E$299,IF(filtro_renovacao="Todos","*",filtro_renovacao),Base!$D$5:$D$299,">="&A28,Base!$D$5:$D$299,"<"&DATE(YEAR(A28),MONTH(A28)+1,1)) -> 801 | C28: =COUNTIFS(Base!$C$5:$C$299,IF(filtro_plano="Todos","*",filtro_plano),Base!$G$5:$G$299,IF(filtro_tipo="Todos","*",filtro_tipo),Base!$E$5:$E$299,IF(filtro_renovacao="Todos","*",filtro_renovacao),Base!$D$5:$D$299,">="&A28,Base!$D$5:$D$299,"<"&DATE(YEAR(A28),MONTH(A28)+1,1)) -> 31 | E28: Ultimate | F28: =SUMIFS(Base!$M$5:$M$299,Base!$C$5:$C$299,IF(filtro_plano="Todos","*",filtro_plano),Base!$G$5:$G$299,IF(filtro_tipo="Todos","*",filtro_tipo),Base!$E$5:$E$299,IF(filtro_renovacao="Todos","*",filtro_renovacao),Base!$C$5:$C$299,E28) -> 5388 | G28: =COUNTIFS(Base!$C$5:$C$299,IF(filtro_plano="Todos","*",filtro_plano),Base!$G$5:$G$299,IF(filtro_tipo="Todos","*",filtro_tipo),Base!$E$5:$E$299,IF(filtro_renovacao="Todos","*",filtro_renovacao),Base!$C$5:$C$299,E28) -> 98
A29: 45383 | B29: =SUMIFS(Base!$M$5:$M$299,Base!$C$5:$C$299,IF(filtro_plano="Todos","*",filtro_plano),Base!$G$5:$G$299,IF(filtro_tipo="Todos","*",filtro_tipo),Base!$E$5:$E$299,IF(filtro_renovacao="Todos","*",filtro_renovacao),Base!$D$5:$D$299,">="&A29,Base!$D$5:$D$299,"<"&DATE(YEAR(A29),MONTH(A29)+1,1)) -> 782 | C29: =COUNTIFS(Base!$C$5:$C$299,IF(filtro_plano="Todos","*",filtro_plano),Base!$G$5:$G$299,IF(filtro_tipo="Todos","*",filtro_tipo),Base!$E$5:$E$299,IF(filtro_renovacao="Todos","*",filtro_renovacao),Base!$D$5:$D$299,">="&A29,Base!$D$5:$D$299,"<"&DATE(YEAR(A29),MONTH(A29)+1,1)) -> 30
A30: 45413 | B30: =SUMIFS(Base!$M$5:$M$299,Base!$C$5:$C$299,IF(filtro_plano="Todos","*",filtro_plano),Base!$G$5:$G$299,IF(filtro_tipo="Todos","*",filtro_tipo),Base!$E$5:$E$299,IF(filtro_renovacao="Todos","*",filtro_renovacao),Base!$D$5:$D$299,">="&A30,Base!$D$5:$D$299,"<"&DATE(YEAR(A30),MONTH(A30)+1,1)) -> 777 | C30: =COUNTIFS(Base!$C$5:$C$299,IF(filtro_plano="Todos","*",filtro_plano),Base!$G$5:$G$299,IF(filtro_tipo="Todos","*",filtro_tipo),Base!$E$5:$E$299,IF(filtro_renovacao="Todos","*",filtro_renovacao),Base!$D$5:$D$299,">="&A30,Base!$D$5:$D$299,"<"&DATE(YEAR(A30),MONTH(A30)+1,1)) -> 31
A31: 45444 | B31: =SUMIFS(Base!$M$5:$M$299,Base!$C$5:$C$299,IF(filtro_plano="Todos","*",filtro_plano),Base!$G$5:$G$299,IF(filtro_tipo="Todos","*",filtro_tipo),Base!$E$5:$E$299,IF(filtro_renovacao="Todos","*",filtro_renovacao),Base!$D$5:$D$299,">="&A31,Base!$D$5:$D$299,"<"&DATE(YEAR(A31),MONTH(A31)+1,1)) -> 770 | C31: =COUNTIFS(Base!$C$5:$C$299,IF(filtro_plano="Todos","*",filtro_plano),Base!$G$5:$G$299,IF(filtro_tipo="Todos","*",filtro_tipo),Base!$E$5:$E$299,IF(filtro_renovacao="Todos","*",filtro_renovacao),Base!$D$5:$D$299,">="&A31,Base!$D$5:$D$299,"<"&DATE(YEAR(A31),MONTH(A31)+1,1)) -> 30
A32: 45474 | B32: =SUMIFS(Base!$M$5:$M$299,Base!$C$5:$C$299,IF(filtro_plano="Todos","*",filtro_plano),Base!$G$5:$G$299,IF(filtro_tipo="Todos","*",filtro_tipo),Base!$E$5:$E$299,IF(filtro_renovacao="Todos","*",filtro_renovacao),Base!$D$5:$D$299,">="&A32,Base!$D$5:$D$299,"<"&DATE(YEAR(A32),MONTH(A32)+1,1)) -> 784 | C32: =COUNTIFS(Base!$C$5:$C$299,IF(filtro_plano="Todos","*",filtro_plano),Base!$G$5:$G$299,IF(filtro_tipo="Todos","*",filtro_tipo),Base!$E$5:$E$299,IF(filtro_renovacao="Todos","*",filtro_renovacao),Base!$D$5:$D$299,">="&A32,Base!$D$5:$D$299,"<"&DATE(YEAR(A32),MONTH(A32)+1,1)) -> 31 | E32: Periodicidade | F32: Receita | G32: Assinantes | I32: Plano | J32: EA Play | K32: Minecraft | L32: Receita total
A33: 45505 | B33: =SUMIFS(Base!$M$5:$M$299,Base!$C$5:$C$299,IF(filtro_plano="Todos","*",filtro_plano),Base!$G$5:$G$299,IF(filtro_tipo="Todos","*",filtro_tipo),Base!$E$5:$E$299,IF(filtro_renovacao="Todos","*",filtro_renovacao),Base!$D$5:$D$299,">="&A33,Base!$D$5:$D$299,"<"&DATE(YEAR(A33),MONTH(A33)+1,1)) -> 787 | C33: =COUNTIFS(Base!$C$5:$C$299,IF(filtro_plano="Todos","*",filtro_plano),Base!$G$5:$G$299,IF(filtro_tipo="Todos","*",filtro_tipo),Base!$E$5:$E$299,IF(filtro_renovacao="Todos","*",filtro_renovacao),Base!$D$5:$D$299,">="&A33,Base!$D$5:$D$299,"<"&DATE(YEAR(A33),MONTH(A33)+1,1)) -> 31 | E33: Monthly | F33: =SUMIFS(Base!$M$5:$M$299,Base!$C$5:$C$299,IF(filtro_plano="Todos","*",filtro_plano),Base!$G$5:$G$299,IF(filtro_tipo="Todos","*",filtro_tipo),Base!$E$5:$E$299,IF(filtro_renovacao="Todos","*",filtro_renovacao),Base!$G$5:$G$299,E33) -> 3571 | G33: =COUNTIFS(Base!$C$5:$C$299,IF(filtro_plano="Todos","*",filtro_plano),Base!$G$5:$G$299,IF(filtro_tipo="Todos","*",filtro_tipo),Base!$E$5:$E$299,IF(filtro_renovacao="Todos","*",filtro_renovacao),Base!$G$5:$G$299,E33) -> 139 | I33: Core | J33: =SUMIFS(Base!$I$5:$I$299,Base!$C$5:$C$299,IF(filtro_plano="Todos","*",filtro_plano),Base!$G$5:$G$299,IF(filtro_tipo="Todos","*",filtro_tipo),Base!$E$5:$E$299,IF(filtro_renovacao="Todos","*",filtro_renovacao),Base!$C$5:$C$299,I33) -> 0 | K33: =SUMIFS(Base!$K$5:$K$299,Base!$C$5:$C$299,IF(filtro_plano="Todos","*",filtro_plano),Base!$G$5:$G$299,IF(filtro_tipo="Todos","*",filtro_tipo),Base!$E$5:$E$299,IF(filtro_renovacao="Todos","*",filtro_renovacao),Base!$C$5:$C$299,I33) -> 0 | L33: =SUMIFS(Base!$M$5:$M$299,Base!$C$5:$C$299,IF(filtro_plano="Todos","*",filtro_plano),Base!$G$5:$G$299,IF(filtro_tipo="Todos","*",filtro_tipo),Base!$E$5:$E$299,IF(filtro_renovacao="Todos","*",filtro_renovacao),Base!$C$5:$C$299,I33) -> 444
A34: 45536 | B34: =SUMIFS(Base!$M$5:$M$299,Base!$C$5:$C$299,IF(filtro_plano="Todos","*",filtro_plano),Base!$G$5:$G$299,IF(filtro_tipo="Todos","*",filtro_tipo),Base!$E$5:$E$299,IF(filtro_renovacao="Todos","*",filtro_renovacao),Base!$D$5:$D$299,">="&A34,Base!$D$5:$D$299,"<"&DATE(YEAR(A34),MONTH(A34)+1,1)) -> 780 | C34: =COUNTIFS(Base!$C$5:$C$299,IF(filtro_plano="Todos","*",filtro_plano),Base!$G$5:$G$299,IF(filtro_tipo="Todos","*",filtro_tipo),Base!$E$5:$E$299,IF(filtro_renovacao="Todos","*",filtro_renovacao),Base!$D$5:$D$299,">="&A34,Base!$D$5:$D$299,"<"&DATE(YEAR(A34),MONTH(A34)+1,1)) -> 30 | E34: Quarterly | F34: =SUMIFS(Base!$M$5:$M$299,Base!$C$5:$C$299,IF(filtro_plano="Todos","*",filtro_plano),Base!$G$5:$G$299,IF(filtro_tipo="Todos","*",filtro_tipo),Base!$E$5:$E$299,IF(filtro_renovacao="Todos","*",filtro_renovacao),Base!$G$5:$G$299,E34) -> 2308 | G34: =COUNTIFS(Base!$C$5:$C$299,IF(filtro_plano="Todos","*",filtro_plano),Base!$G$5:$G$299,IF(filtro_tipo="Todos","*",filtro_tipo),Base!$E$5:$E$299,IF(filtro_renovacao="Todos","*",filtro_renovacao),Base!$G$5:$G$299,E34) -> 85 | I34: Standard | J34: =SUMIFS(Base!$I$5:$I$299,Base!$C$5:$C$299,IF(filtro_plano="Todos","*",filtro_plano),Base!$G$5:$G$299,IF(filtro_tipo="Todos","*",filtro_tipo),Base!$E$5:$E$299,IF(filtro_renovacao="Todos","*",filtro_renovacao),Base!$C$5:$C$299,I34) -> 0 | K34: =SUMIFS(Base!$K$5:$K$299,Base!$C$5:$C$299,IF(filtro_plano="Todos","*",filtro_plano),Base!$G$5:$G$299,IF(filtro_tipo="Todos","*",filtro_tipo),Base!$E$5:$E$299,IF(filtro_renovacao="Todos","*",filtro_renovacao),Base!$C$5:$C$299,I34) -> 1920 | L34: =SUMIFS(Base!$M$5:$M$299,Base!$C$5:$C$299,IF(filtro_plano="Todos","*",filtro_plano),Base!$G$5:$G$299,IF(filtro_tipo="Todos","*",filtro_tipo),Base!$E$5:$E$299,IF(filtro_renovacao="Todos","*",filtro_renovacao),Base!$C$5:$C$299,I34) -> 1801
A35: 45566 | B35: =SUMIFS(Base!$M$5:$M$299,Base!$C$5:$C$299,IF(filtro_plano="Todos","*",filtro_plano),Base!$G$5:$G$299,IF(filtro_tipo="Todos","*",filtro_tipo),Base!$E$5:$E$299,IF(filtro_renovacao="Todos","*",filtro_renovacao),Base!$D$5:$D$299,">="&A35,Base!$D$5:$D$299,"<"&DATE(YEAR(A35),MONTH(A35)+1,1)) -> 832 | C35: =COUNTIFS(Base!$C$5:$C$299,IF(filtro_plano="Todos","*",filtro_plano),Base!$G$5:$G$299,IF(filtro_tipo="Todos","*",filtro_tipo),Base!$E$5:$E$299,IF(filtro_renovacao="Todos","*",filtro_renovacao),Base!$D$5:$D$299,">="&A35,Base!$D$5:$D$299,"<"&DATE(YEAR(A35),MONTH(A35)+1,1)) -> 31 | E35: Annual | F35: =SUMIFS(Base!$M$5:$M$299,Base!$C$5:$C$299,IF(filtro_plano="Todos","*",filtro_plano),Base!$G$5:$G$299,IF(filtro_tipo="Todos","*",filtro_tipo),Base!$E$5:$E$299,IF(filtro_renovacao="Todos","*",filtro_renovacao),Base!$G$5:$G$299,E35) -> 1754 | G35: =COUNTIFS(Base!$C$5:$C$299,IF(filtro_plano="Todos","*",filtro_plano),Base!$G$5:$G$299,IF(filtro_tipo="Todos","*",filtro_tipo),Base!$E$5:$E$299,IF(filtro_renovacao="Todos","*",filtro_renovacao),Base!$G$5:$G$299,E35) -> 71 | I35: Ultimate | J35: =SUMIFS(Base!$I$5:$I$299,Base!$C$5:$C$299,IF(filtro_plano="Todos","*",filtro_plano),Base!$G$5:$G$299,IF(filtro_tipo="Todos","*",filtro_tipo),Base!$E$5:$E$299,IF(filtro_renovacao="Todos","*",filtro_renovacao),Base!$C$5:$C$299,I35) -> 2940 | K35: =SUMIFS(Base!$K$5:$K$299,Base!$C$5:$C$299,IF(filtro_plano="Todos","*",filtro_plano),Base!$G$5:$G$299,IF(filtro_tipo="Todos","*",filtro_tipo),Base!$E$5:$E$299,IF(filtro_renovacao="Todos","*",filtro_renovacao),Base!$C$5:$C$299,I35) -> 1960 | L35: =SUMIFS(Base!$M$5:$M$299,Base!$C$5:$C$299,IF(filtro_plano="Todos","*",filtro_plano),Base!$G$5:$G$299,IF(filtro_tipo="Todos","*",filtro_tipo),Base!$E$5:$E$299,IF(filtro_renovacao="Todos","*",filtro_renovacao),Base!$C$5:$C$299,I35) -> 5388
A36: 45597 | B36: =SUMIFS(Base!$M$5:$M$299,Base!$C$5:$C$299,IF(filtro_plano="Todos","*",filtro_plano),Base!$G$5:$G$299,IF(filtro_tipo="Todos","*",filtro_tipo),Base!$E$5:$E$299,IF(filtro_renovacao="Todos","*",filtro_renovacao),Base!$D$5:$D$299,">="&A36,Base!$D$5:$D$299,"<"&DATE(YEAR(A36),MONTH(A36)+1,1)) -> 784 | C36: =COUNTIFS(Base!$C$5:$C$299,IF(filtro_plano="Todos","*",filtro_plano),Base!$G$5:$G$299,IF(filtro_tipo="Todos","*",filtro_tipo),Base!$E$5:$E$299,IF(filtro_renovacao="Todos","*",filtro_renovacao),Base!$D$5:$D$299,">="&A36,Base!$D$5:$D$299,"<"&DATE(YEAR(A36),MONTH(A36)+1,1)) -> 30
A37: 45627 | B37: =SUMIFS(Base!$M$5:$M$299,Base!$C$5:$C$299,IF(filtro_plano="Todos","*",filtro_plano),Base!$G$5:$G$299,IF(filtro_tipo="Todos","*",filtro_tipo),Base!$E$5:$E$299,IF(filtro_renovacao="Todos","*",filtro_renovacao),Base!$D$5:$D$299,">="&A37,Base!$D$5:$D$299,"<"&DATE(YEAR(A37),MONTH(A37)+1,1)) -> 389 | C37: =COUNTIFS(Base!$C$5:$C$299,IF(filtro_plano="Todos","*",filtro_plano),Base!$G$5:$G$299,IF(filtro_tipo="Todos","*",filtro_tipo),Base!$E$5:$E$299,IF(filtro_renovacao="Todos","*",filtro_renovacao),Base!$D$5:$D$299,">="&A37,Base!$D$5:$D$299,"<"&DATE(YEAR(A37),MONTH(A37)+1,1)) -> 16
A40: Leitura recomendada: os gráficos respondem aos filtros do Dashboard. A seção de perguntas do desafio usa sempre a base completa para preservar respostas comparáveis. Dezembro contém dados somente até 16/12/2024.

Sheet Base
A1: BASE DE ASSINATURAS | J1: PROJETO AUTORAL • DIO
J2: DASHBOARD | K2: ANÁLISE | L2: BASE | M2: DICIONÁRIO | N2: GUIA
A3: Cópia normalizada da base didática: o hífen de EA Play Price foi convertido em zero para permitir cálculos.
A4: Subscriber ID | B4: Name | C4: Plan | D4: Start Date | E4: Auto Renewal | F4: Subscription Price | G4: Subscription Type | H4: EA Play Season Pass | I4: EA Play Season Pass Price | J4: Minecraft Season Pass | K4: Minecraft Season Pass Price | L4: Coupon Value | M4: Total Value | N4: Calculated Value | O4: Validation | P4: Month
A5: 3231 | B5: João Silva | C5: Ultimate | D5: 45292 | E5: Yes | F5: 15 | G5: Monthly | H5: Yes | I5: 30 | J5: Yes | K5: 20 | L5: 5 | M5: 60 | N5: =F5+I5+K5-L5 -> 60 | O5: =IF(ABS(M5-N5)<0.001,"OK","REVIEW") -> OK | P5: =DATE(YEAR(D5),MONTH(D5),1) -> 45292
A6: 3232 | B6: Maria Oliveira | C6: Core | D6: 45306 | E6: No | F6: 5 | G6: Annual | H6: No | I6: 0 | J6: No | K6: 0 | L6: 0 | M6: 5 | N6: =F6+I6+K6-L6 -> 5 | O6: =IF(ABS(M6-N6)<0.001,"OK","REVIEW") -> OK | P6: =DATE(YEAR(D6),MONTH(D6),1) -> 45292
A7: 3233 | B7: Lucas Fernandes | C7: Standard | D7: 45332 | E7: Yes | F7: 10 | G7: Quarterly | H7: No | I7: 0 | J7: Yes | K7: 20 | L7: 10 | M7: 20 | N7: =F7+I7+K7-L7 -> 20 | O7: =IF(ABS(M7-N7)<0.001,"OK","REVIEW") -> OK | P7: =DATE(YEAR(D7),MONTH(D7),1) -> 45323
A8: 3234 | B8: Ana Souza | C8: Ultimate | D8: 45342 | E8: No | F8: 15 | G8: Monthly | H8: Yes | I8: 30 | J8: Yes | K8: 20 | L8: 3 | M8: 62 | N8: =F8+I8+K8-L8 -> 62 | O8: =IF(ABS(M8-N8)<0.001,"OK","REVIEW") -> OK | P8: =DATE(YEAR(D8),MONTH(D8),1) -> 45323
A9: 3235 | B9: Pedro Gonçalves | C9: Core | D9: 45356 | E9: Yes | F9: 5 | G9: Monthly | H9: No | I9: 0 | J9: No | K9: 0 | L9: 1 | M9: 4 | N9: =F9+I9+K9-L9 -> 4 | O9: =IF(ABS(M9-N9)<0.001,"OK","REVIEW") -> OK | P9: =DATE(YEAR(D9),MONTH(D9),1) -> 45352
A10: 3236 | B10: Felipe Costa | C10: Standard | D10: 45353 | E10: No | F10: 10 | G10: Monthly | H10: No | I10: 0 | J10: Yes | K10: 20 | L10: 2 | M10: 28 | N10: =F10+I10+K10-L10 -> 28 | O10: =IF(ABS(M10-N10)<0.001,"OK","REVIEW") -> OK | P10: =DATE(YEAR(D10),MONTH(D10),1) -> 45352
A11: 3237 | B11: Camila Ribeiro | C11: Ultimate | D11: 45354 | E11: Yes | F11: 15 | G11: Quarterly | H11: Yes | I11: 30 | J11: Yes | K11: 20 | L11: 10 | M11: 55 | N11: =F11+I11+K11-L11 -> 55 | O11: =IF(ABS(M11-N11)<0.001,"OK","REVIEW") -> OK | P11: =DATE(YEAR(D11),MONTH(D11),1) -> 45352
A12: 3238 | B12: André Mendes | C12: Core | D12: 45355 | E12: Yes | F12: 5 | G12: Annual | H12: No | I12: 0 | J12: No | K12: 0 | L12: 0 | M12: 5 | N12: =F12+I12+K12-L12 -> 5 | O12: =IF(ABS(M12-N12)<0.001,"OK","REVIEW") -> OK | P12: =DATE(YEAR(D12),MONTH(D12),1) -> 45352
A13: 3239 | B13: Sofia Almeida | C13: Ultimate | D13: 45356 | E13: No | F13: 15 | G13: Monthly | H13: Yes | I13: 30 | J13: Yes | K13: 20 | L13: 5 | M13: 60 | N13: =F13+I13+K13-L13 -> 60 | O13: =IF(ABS(M13-N13)<0.001,"OK","REVIEW") -> OK | P13: =DATE(YEAR(D13),MONTH(D13),1) -> 45352
A14: 3240 | B14: Bruno Martins | C14: Standard | D14: 45357 | E14: Yes | F14: 10 | G14: Quarterly | H14: No | I14: 0 | J14: Yes | K14: 20 | L14: 15 | M14: 15 | N14: =F14+I14+K14-L14 -> 15 | O14: =IF(ABS(M14-N14)<0.001,"OK","REVIEW") -> OK | P14: =DATE(YEAR(D14),MONTH(D14),1) -> 45352
A15: 3241 | B15: Rita Castro | C15: Core | D15: 45358 | E15: No | F15: 5 | G15: Monthly | H15: No | I15: 0 | J15: No | K15: 0 | L15: 1 | M15: 4 | N15: =F15+I15+K15-L15 -> 4 | O15: =IF(ABS(M15-N15)<0.001,"OK","REVIEW") -> OK | P15: =DATE(YEAR(D15),MONTH(D15),1) -> 45352
A16: 3242 | B16: Marco Túlio | C16: Ultimate | D16: 45359 | E16: Yes | F16: 15 | G16: Annual | H16: Yes | I16: 30 | J16: Yes | K16: 20 | L16: 20 | M16: 45 | N16: =F16+I16+K16-L16 -> 45 | O16: =IF(ABS(M16-N16)<0.001,"OK","REVIEW") -> OK | P16: =DATE(YEAR(D16),MONTH(D16),1) -> 45352
... A299: 3525 | B299: Elisa Magalhães | C299: Core | D299: 45642 | E299: No | F299: 5 | G299: Monthly | H299: No | I299: 0 | J299: No | K299: 0 | L299: 1 | M299: 4 | N299: =F299+I299+K299-L299 -> 4 | O299: =IF(ABS(M299-N299)<0.001,"OK","REVIEW") -> OK | P299: =DATE(YEAR(D299),MONTH(D299),1) -> 45627

Sheet Dicionário
A1: DICIONÁRIO DE DADOS | J1: PROJETO AUTORAL • DIO
J2: DASHBOARD | K2: ANÁLISE | L2: BASE | M2: DICIONÁRIO | N2: GUIA
A3: Definições, tratamento aplicado e uso de cada campo da base didática.
B5: Campo | C5: Tipo | D5: Descrição | E5: Tratamento / uso
B6: Subscriber ID | C6: Inteiro | D6: Identificador único do registro. | E6: Chave primária; 295 valores únicos.
B7: Name | C7: Texto | D7: Nome didático do assinante. | E7: Não é usado como chave porque pode se repetir.
B8: Plan | C8: Categoria | D8: Core, Standard ou Ultimate. | E8: Filtro e agrupamento de receita.
B9: Start Date | C9: Data | D9: Data inicial da assinatura em 2024. | E9: Agrupamento mensal e definição do período.
B10: Auto Renewal | C10: Categoria | D10: Yes ou No para renovação automática. | E10: Filtro, taxa de recorrência e análise anual.
B11: Subscription Price | C11: Moeda | D11: Preço-base da assinatura. | E11: Componente positivo do valor final.
B12: Subscription Type | C12: Categoria | D12: Monthly, Quarterly ou Annual. | E12: Filtro e comparação de periodicidade.
B13: EA Play Season Pass | C13: Categoria | D13: Adesão ao passe EA Play. | E13: Contexto do adicional.
B14: EA Play Season Pass Price | C14: Moeda | D14: Valor do EA Play. | E14: Hífens da fonte convertidos em zero.
B15: Minecraft Season Pass | C15: Categoria | D15: Adesão ao passe Minecraft. | E15: Contexto do adicional.
B16: Minecraft Season Pass Price | C16: Moeda | D16: Valor do passe Minecraft. | E16: Componente positivo do valor final.
... B21: Month | C21: Fórmula/Data | D21: Primeiro dia do mês de Start Date. | E21: Apoio para análise temporal.
B24: QUALIDADE DA BASE: 295 IDs únicos, nenhuma linha vazia na tabela e 295 valores finais conferidos pela fórmula Subscription Price + EA Play + Minecraft − Coupon. O período vai de 01/01/2024 a 16/12/2024; dezembro é parcial.
B28: FONTE: base didática disponibilizada como material de apoio do desafio DIO. O arquivo original permanece em data/base.xlsx; a aba Base contém a versão normalizada usada nos cálculos.

Sheet Guia
A1: GUIA E MÉTODO ABCDE | J1: PROJETO AUTORAL • DIO
J2: DASHBOARD | K2: ANÁLISE | L2: BASE | M2: DICIONÁRIO | N2: GUIA
A3: Como atualizar, interpretar e reproduzir o Xbox Sales Pulse.
B5: A — Assets | C5: Identidade visual autoral: verde, grafite, azul e roxo. Nenhum logo oficial foi incorporado ao arquivo.
B8: B — Base | C8: A aba Base possui 295 assinaturas normalizadas. A fonte original permanece em data/base.xlsx para auditoria.
B11: C — Cálculos | C11: A aba Análise usa SUMIFS, COUNTIFS, IFERROR, COUNTIF, SUM e fórmulas de datas. Os blocos alimentam todos os gráficos.
B14: D — Dashboard | C14: Escolha Plano, Periodicidade e Renovação nas células verdes. Cartões e quatro gráficos recalculam automaticamente.
B17: E — Entrega | C17: O repositório inclui Excel final, base original, CSV normalizado, README, prévias, metodologia e scripts de validação.
B20: Atualizar dados | C20: Substitua ou acrescente registros na aba Base mantendo as colunas. Se ultrapassar 295 linhas, amplie os intervalos das fórmulas e a tabela.
B23: Perguntas do desafio | C23: Análise registra a receita anual total, anual com/sem renovação, EA Play e Minecraft. Os valores usam a base completa.
B26: Contexto | C26: Janeiro e fevereiro têm apenas 2 registros cada; dezembro termina em 16/12. Não interprete a evolução mensal como série completa de demanda.
B29: Compatibilidade | C29: Recomendado Microsoft Excel 2016 ou superior. Não há macros, APIs, conexões externas ou necessidade de Atualizar Tudo.
B32: Reprodução | C32: Execute scripts/gerar_dashboard.py, scripts/gerar_previas.py e scripts/verificar_dashboard.py após instalar requirements.txt.
B35: Autoria: 0Barone (@gabrielnasciimentoleandro-arch). Projeto educacional e não oficial. Xbox, Game Pass, EA Play e Minecraft são marcas de seus respectivos titulares.
B39: VOLTAR AO DASHBOARD

Sheet Apoio
A1: Listas internas para filtros
A3: lista_planos | B3: lista_tipos | C3: lista_renovacao
A4: Todos | B4: Todos | C4: Todos
A5: Core | B5: Monthly | C5: Yes
A6: Standard | B6: Quarterly | C6: No
A7: Ultimate | B7: Annual
